rtwo/__init__.py
rtwo/compute.py
rtwo/driver.py
rtwo/exceptions.py
rtwo/linktest.py
rtwo/meta.py
rtwo/settings.py
rtwo/version.py
rtwo/accounts/__init__.py
rtwo/accounts/openstack.py
rtwo/drivers/__init__.py
rtwo/drivers/aws.py
rtwo/drivers/common.py
rtwo/drivers/eucalyptus.py
rtwo/drivers/eucalyptus_user.py
rtwo/drivers/irods_store.py
rtwo/drivers/openstack_facade.py
rtwo/drivers/openstack_network.py
rtwo/drivers/openstack_user.py
rtwo/mixins/__init__.py
rtwo/mixins/driver.py
rtwo/models/__init__.py
rtwo/models/identity.py
rtwo/models/instance.py
rtwo/models/machine.py
rtwo/models/provider.py
rtwo/models/size.py
rtwo/models/volume.py
rtwo/test/__init__.py
rtwo/test/test_openstack.py
rtwo-0.5.25.dist-info/AUTHORS
rtwo-0.5.25.dist-info/LICENSE
rtwo-0.5.25.dist-info/METADATA
rtwo-0.5.25.dist-info/WHEEL
rtwo-0.5.25.dist-info/top_level.txt
rtwo-0.5.25.dist-info/RECORD
