Metadata-Version: 2.1
Name: rtwo
Version: 0.5.25
Summary: A unified interface into multiple cloud providers.
Home-page: https://github.com/iPlantCollaborativeOpenSource/rtwo
Author: iPlant Collaborative
Author-email: atmodevs@gmail.com
License: BSD License, 3 clause
Platform: UNKNOWN
Classifier: Development Status :: 4 - Beta
Classifier: Intended Audience :: Developers
Classifier: Intended Audience :: System Administrators
Classifier: Intended Audience :: Information Technology
Classifier: License :: OSI Approved :: BSD License
Classifier: Operating System :: OS Independent
Classifier: Programming Language :: Python
Classifier: Topic :: Software Development :: Libraries
Classifier: Topic :: System
Classifier: Topic :: System :: Clustering
Classifier: Topic :: System :: Distributed Computing
Classifier: Topic :: System :: Systems Administration
Requires-Dist: requests
Requires-Dist: apache-libcloud (==0.20.1)
Requires-Dist: threepio (==0.2.0)
Requires-Dist: rfive (==0.2.0)
Requires-Dist: python-irodsclient
Requires-Dist: python-cinderclient (==1.9.0)
Requires-Dist: python-glanceclient (==2.5.0)
Requires-Dist: python-heatclient (==1.11.0)
Requires-Dist: python-keystoneclient (==3.6.0)
Requires-Dist: python-neutronclient (==6.0.0)
Requires-Dist: python-novaclient (==6.0.0)
Requires-Dist: python-saharaclient (==1.2.0)
Requires-Dist: python-swiftclient (==3.3.0)
Requires-Dist: python-openstackclient (==3.3.0)
